LaTexShortcuts/__init__.py
LaTex_Shortcuts-0.0.4.dist-info/LICENSE
LaTex_Shortcuts-0.0.4.dist-info/METADATA
LaTex_Shortcuts-0.0.4.dist-info/WHEEL
LaTex_Shortcuts-0.0.4.dist-info/top_level.txt
LaTex_Shortcuts-0.0.4.dist-info/RECORD
