Metadata-Version: 2.1
Name: LaTex-Shortcuts
Version: 0.0.4
Summary: A small example package
Home-page: https://github.com/AriaBagheri/LatexShortcuts
Author: Aria Bagheri
Author-email: ariab9342@gmail.com
License: UNKNOWN
Platform: UNKNOWN
Classifier: Programming Language :: Python :: 3
Classifier: License :: OSI Approved :: MIT License
Classifier: Operating System :: OS Independent
Requires-Python: >=3.6
